{
    "django": {
        "expressions": {
            "math": {
                "addition": "Could not parse the remainder: ' + 3' from '2 + 3'",
                "devision": "Could not parse the remainder: '/5' from '10/5'",
                "multiplication": "Could not parse the remainder: '*2' from '5*2'",
                "power": "Could not parse the remainder: '**3' from '2**3'",
                "subtraction": "Could not parse the remainder: ' - 3' from '5 - 3'"
            }
        },
        "filters": {
            "abs": {
                "negative-float": "Invalid filter: 'abs'",
                "negative-integer": "Invalid filter: 'abs'",
                "positive-float": "Invalid filter: 'abs'",
                "positive-integer": "Invalid filter: 'abs'",
                "variable": "Invalid filter: 'abs'",
                "zero": "Invalid filter: 'abs'"
            },
            "batch": {
                "size-and-fill": "'for' statements should use the format 'for x in y': for row in items|batch(3, 'No item')",
                "size-only": "Invalid filter: 'batch'"
            },
            "capitalize": {
                "mixed-case": "Invalid filter: 'capitalize'",
                "number": "Invalid filter: 'capitalize'",
                "sentence": "Invalid filter: 'capitalize'",
                "starts-with-number": "Invalid filter: 'capitalize'",
                "word": "Invalid filter: 'capitalize'"
            },
            "center": {
                "default": "center requires 2 arguments, 1 provided",
                "width-20": "center requires 2 arguments, 1 provided"
            },
            "default": {
                "alias-d": "Invalid filter: 'd'",
                "empty-string-strict": "default requires 2 arguments, 1 provided",
                "empty-string": "default requires 2 arguments, 1 provided",
                "undefined-property-bracket-notation": "Could not parse some characters: vars|['x']||default('\"x\" on \"vars\" is not defined')",
                "undefined-property-dot-notation": "default requires 2 arguments, 1 provided",
                "undefined-variable": "default requires 2 arguments, 1 provided"
            },
            "dictsort": {
                "by-value": "Invalid block tag on line 1: '-'. Did you forget to register or load this tag?",
                "case-insensitive": "Invalid block tag on line 1: '-'. Did you forget to register or load this tag?",
                "case-sensitive": "Invalid block tag on line 1: '-'. Did you forget to register or load this tag?",
                "default": "Invalid block tag on line 1: '-'. Did you forget to register or load this tag?"
            },
            "first": {
                "array": "Could not parse some characters: |[1, 2, 3, 4]||first",
                "number": "'int' object has no attribute '__getitem__'",
                "object": "Could not parse some characters: |{ a: 1, b: 2, c: 3, d: 4 }||first"
            }
        },
        "tags": {
            "raw": {
                "broken-expression": "Invalid block tag on line 1: 'raw'. Did you forget to register or load this tag?",
                "broken-tag": "Invalid block tag on line 1: 'raw'. Did you forget to register or load this tag?",
                "comment": "Invalid block tag on line 1: 'raw'. Did you forget to register or load this tag?",
                "multiline": "Invalid block tag on line 2: 'raw'. Did you forget to register or load this tag?",
                "multiple": "Invalid block tag on line 1: 'raw'. Did you forget to register or load this tag?",
                "nested-raw": "Invalid block tag on line 1: 'raw'. Did you forget to register or load this tag?",
                "tag": "Invalid block tag on line 1: 'raw'. Did you forget to register or load this tag?",
                "text": "Invalid block tag on line 1: 'raw'. Did you forget to register or load this tag?"
            }
        }
    },
    "jinja2": {
        "filters": {
            "default": {
                "undefined-property-bracket-notation": "'vars' is undefined",
                "undefined-property-dot-notation": "'vars' is undefined"
            },
            "first": {
                "number": "'int' object is not iterable"
            }
        },
        "tags": {
            "raw": {
                "nested-raw": "Encountered unknown tag 'endraw'."
            }
        }
    },
    "nunjucks": {
        "filters": {
            "capitalize": {
                "number": "\n  TypeError: str.toLowerCase is not a function"
            }
        }
    },
    "swig": {
        "expressions": {
            "math": {
                "power": "SyntaxError: Unexpected token *."
            },
            "reserved-words": {
                "function": "Reserved keyword \"function\" attempted to be used as a variable.",
                "var": "Reserved keyword \"var\" attempted to be used as a variable."
            }
        },
        "filters": {
            "abs": {
                "negative-float": "Invalid filter \"abs\".",
                "negative-integer": "Invalid filter \"abs\".",
                "positive-float": "Invalid filter \"abs\".",
                "positive-integer": "Invalid filter \"abs\".",
                "variable": "Invalid filter \"abs\".",
                "zero": "Invalid filter \"abs\"."
            },
            "batch": {
                "size-and-fill": "Invalid filter \"batch\".",
                "size-only": "Invalid filter \"batch\"."
            },
            "center": {
                "default": "Invalid filter \"center\".",
                "width-20": "Invalid filter \"center\"."
            },
            "default": {
                "alias-d": "Invalid filter \"d\"."
            },
            "dictsort": {
                "by-value": "Invalid filter \"dictsort\".",
                "case-insensitive": "Invalid filter \"dictsort\".",
                "case-sensitive": "Invalid filter \"dictsort\".",
                "default": "Invalid filter \"dictsort\"."
            }
        },
        "tags": {
            "raw": {
                "nested-raw": "Unexpected end of tag \"raw\"."
            }
        }
    },
    "twig": {
        "filters": {
            "center": {
                "default": "Unknown \"center\" filter.",
                "width-20": "Unknown \"center\" filter."
            },
            "default": {
                "alias-d": "Unknown \"d\" filter. Did you mean \"date\", \"round\", \"default\", \"url_encode\", \"date_modify\", \"json_encode\", \"convert_encoding\"?"
            },
            "dictsort": {
                "by-value": "Unknown \"dictsort\" filter.",
                "case-insensitive": "Unknown \"dictsort\" filter.",
                "case-sensitive": "Unknown \"dictsort\" filter.",
                "default": "Unknown \"dictsort\" filter."
            }
        },
        "tags": {
            "raw": {
                "nested-raw": "Unknown \"endraw\" tag."
            }
        }
    }
}